nonebot_plugin_gotify-1.0.9.dist-info/METADATA
nonebot_plugin_gotify-1.0.9.dist-info/WHEEL
nonebot_plugin_gotify-1.0.9.dist-info/entry_points.txt
nonebot_plugin_gotify-1.0.9.dist-info/licenses/LICENSE
nonebot_plugin_gotify/__init__.py
nonebot_plugin_gotify/adapter_ctx.py
nonebot_plugin_gotify/config.py
nonebot_plugin_gotify/gotify.py
nonebot_plugin_gotify-1.0.9.dist-info/RECORD
