Metadata-Version: 2.1
Name: nonebot-plugin-gotify
Version: 1.0.9
Summary: Default template for PDM package
Author-Email: snowykami <snowykami@outlook.com>
License: MIT
Requires-Python: >=3.10
Requires-Dist: nonebot2>=2.3.3
Requires-Dist: aiohttp>=3.10.10
Requires-Dist: magicoca>=1.0.5
